{
  "match": {
    "id": 421,
    "attendance": 12000,
    "count_attendance": 1,
    "card_type_id": 1,
    "verified": 1,
    "referee_id": 249,
    "trackcommissioner_id": 271,
    "broadcaster_schedule_id": null,
    "status_id": 1,
    "season": 2015,
    "match_type_id": 1,
    "match_subtype_id": 1,
    "track_id": 24,
    "has_telemetry": 0,
    "name": {
      "pl": "SPAR Falubaz Zielona Góra - PGE Stal Rzeszów",
      "en": "SPAR Falubaz Zielona Góra - PGE Stal Rzeszów"
    },
    "shortname": {
      "pl": "ZIE - RZE",
      "en": "ZIE - RZE"
    },
    "description": {
      "pl": "",
      "en": ""
    },
    "datetime_schedule": 1428859800000,
    "datetime_has_hour": 1,
    "round": 2,
    "city": null,
    "card_teams": [
      {
        "no": 1,
        "card_id": 421,
        "team_id": 5,
        "match_score": 50,
        "match_tlt_score": null,
        "position": null,
        "team_manager_id": 563,
        "manager_id": null,
        "coach_id": null,
        "team_shortcut": "ZIE",
        "team_title": "SPAR Falubaz Zielona Góra",
        "coach": null,
        "manager": null,
        "team_manager": "Jacek Frątczak"
      },
      {
        "no": 2,
        "card_id": 421,
        "team_id": 10,
        "match_score": 40,
        "match_tlt_score": null,
        "position": null,
        "team_manager_id": 577,
        "manager_id": null,
        "coach_id": null,
        "team_shortcut": "RZE",
        "team_title": "PGE Stal Rzeszów",
        "coach": null,
        "manager": null,
        "team_manager": "Janusz Dziobak"
      }
    ],
    "status": {
      "id": 1,
      "name": {
        "pl": "Rozegrany",
        "en": "Raced"
      },
      "shortname": {
        "pl": "Rozegrany",
        "en": "Raced"
      }
    },
    "broadcaster_schedule": null,
    "match_type": {
      "id": 1,
      "shortname": {
        "pl": "PGEE",
        "en": "PGEE"
      },
      "name": {
        "pl": "Ekstraliga",
        "en": "Polish Speedway Extraleague"
      },
      "team_competition": 1,
      "has_home_away": 1,
      "has_rounds": 1
    },
    "match_subtype": {
      "id": 1,
      "name": {
        "pl": "Część zasadnicza",
        "en": "Main Round"
      },
      "shortname": {
        "pl": "Część zasadnicza",
        "en": "MR"
      }
    },
    "postponed": null,
    "postponed_first": null,
    "track": {
      "id": 24,
      "city": "Zielona Góra",
      "fullname": "W69"
    },
    "track_commissioner": {
      "id": 271,
      "name": "Józef",
      "surname": "Piekarski"
    },
    "referee": {
      "id": 249,
      "name": "Tomasz",
      "surname": "Proszowski"
    }
  },
  "heats": [
    {
      "id": 4939,
      "canceled": 0,
      "no": 1,
      "restart_id": null,
      "home_heat_score": 3,
      "away_heat_score": 3,
      "home_match_score": 3,
      "away_match_score": 3,
      "results": [
        {
          "heat_id": 4939,
          "rider_id": 69,
          "rider_no": 9,
          "helmet": "red",
          "joker": 0,
          "gate": "b",
          "score": "3",
          "bonus": 0,
          "substitute_id": null,
          "substitute_no": null,
          "warning": null,
          "rider": {
            "id": 69,
            "name": "Jarosław",
            "surname": "Hampel"
          },
          "substitute": null
        },
        {
          "heat_id": 4939,
          "rider_id": 435,
          "rider_no": 10,
          "helmet": "blue",
          "joker": 0,
          "gate": "d",
          "score": "0",
          "bonus": 0,
          "substitute_id": null,
          "substitute_no": null,
          "warning": null,
          "rider": {
            "id": 435,
            "name": "Oleksandr",
            "surname": "Loktayev"
          },
          "substitute": null
        },
        {
          "heat_id": 4939,
          "rider_id": 135,
          "rider_no": 1,
          "helmet": "yellow",
          "joker": 0,
          "gate": "a",
          "score": "2",
          "bonus": 0,
          "substitute_id": null,
          "substitute_no": null,
          "warning": null,
          "rider": {
            "id": 135,
            "name": "Peter",
            "surname": "Ljung"
          },
          "substitute": null
        },
        {
          "heat_id": 4939,
          "rider_id": 546,
          "rider_no": 2,
          "helmet": "white",
          "joker": 0,
          "gate": "c",
          "score": "1",
          "bonus": 1,
          "substitute_id": null,
          "substitute_no": null,
          "warning": null,
          "rider": {
            "id": 546,
            "name": "Mirosław",
            "surname": "Jabłoński"
          },
          "substitute": null
        }
      ]
    },
    {
      "id": 4940,
      "canceled": 0,
      "no": 2,
      "restart_id": null,
      "home_heat_score": 3,
      "away_heat_score": 3,
      "home_match_score": 6,
      "away_match_score": 6,
      "results": [
        {
          "heat_id": 4940,
          "rider_id": 80,
          "rider_no": 14,
          "helmet": "red",
          "joker": 0,
          "gate": "c",
          "score": "2",
          "bonus": 0,
          "substitute_id": null,
          "substitute_no": null,
          "warning": null,
          "rider": {
            "id": 80,
            "name": "Alex",
            "surname": "Zgardziński"
          },
          "substitute": null
        },
        {
          "heat_id": 4940,
          "rider_id": 70,
          "rider_no": 15,
          "helmet": "blue",
          "joker": 0,
          "gate": "a",
          "score": "1",
          "bonus": 1,
          "substitute_id": null,
          "substitute_no": null,
          "warning": null,
          "rider": {
            "id": 70,
            "name": "Krystian",
            "surname": "Pieszczek"
          },
          "substitute": null
        },
        {
          "heat_id": 4940,
          "rider_id": 545,
          "rider_no": 6,
          "helmet": "yellow",
          "joker": 0,
          "gate": "b",
          "score": "3",
          "bonus": 0,
          "substitute_id": null,
          "substitute_no": null,
          "warning": null,
          "rider": {
            "id": 545,
            "name": "Artur",
            "surname": "Czaja"
          },
          "substitute": null
        },
        {
          "heat_id": 4940,
          "rider_id": 124,
          "rider_no": 7,
          "helmet": "white",
          "joker": 0,
          "gate": "d",
          "score": "0",
          "bonus": 0,
          "substitute_id": null,
          "substitute_no": null,
          "warning": null,
          "rider": {
            "id": 124,
            "name": "Krystian",
            "surname": "Rempała"
          },
          "substitute": null
        }
      ]
    },
    {
      "id": 4941,
      "canceled": 1,
      "no": 3,
      "restart_id": null,
      "home_heat_score": 0,
      "away_heat_score": 0,
      "home_match_score": null,
      "away_match_score": null,
      "results": [
        {
          "heat_id": 4941,
          "rider_id": 66,
          "rider_no": 11,
          "helmet": "red",
          "joker": 0,
          "gate": "a",
          "score": null,
          "bonus": 0,
          "substitute_id": null,
          "substitute_no": null,
          "warning": null,
          "rider": {
            "id": 66,
            "name": "Grzegorz",
            "surname": "Walasek"
          },
          "substitute": null
        },
        {
          "heat_id": 4941,
          "rider_id": 147,
          "rider_no": 12,
          "helmet": "blue",
          "joker": 0,
          "gate": "c",
          "score": "U",
          "bonus": 0,
          "substitute_id": null,
          "substitute_no": null,
          "warning": null,
          "rider": {
            "id": 147,
            "name": "Andreas",
            "surname": "Jonsson"
          },
          "substitute": null
        },
        {
          "heat_id": 4941,
          "rider_id": 547,
          "rider_no": 3,
          "helmet": "yellow",
          "joker": 0,
          "gate": "b",
          "score": null,
          "bonus": 0,
          "substitute_id": null,
          "substitute_no": null,
          "warning": null,
          "rider": {
            "id": 547,
            "name": "Dawid",
            "surname": "Lampart"
          },
          "substitute": null
        },
        {
          "heat_id": 4941,
          "rider_id": 59,
          "rider_no": 4,
          "helmet": "white",
          "joker": 0,
          "gate": "d",
          "score": null,
          "bonus": 0,
          "substitute_id": null,
          "substitute_no": null,
          "warning": null,
          "rider": {
            "id": 59,
            "name": "Greg",
            "surname": "Hancock"
          },
          "substitute": null
        }
      ]
    },
    {
      "id": 4954,
      "canceled": 0,
      "no": 3,
      "restart_id": 4941,
      "home_heat_score": 3,
      "away_heat_score": 3,
      "home_match_score": 9,
      "away_match_score": 9,
      "results": [
        {
          "heat_id": 4954,
          "rider_id": 66,
          "rider_no": 11,
          "helmet": "red",
          "joker": 0,
          "gate": "a",
          "score": "2",
          "bonus": 0,
          "substitute_id": null,
          "substitute_no": null,
          "warning": null,
          "rider": {
            "id": 66,
            "name": "Grzegorz",
            "surname": "Walasek"
          },
          "substitute": null
        },
        {
          "heat_id": 4954,
          "rider_id": 147,
          "rider_no": 12,
          "helmet": "blue",
          "joker": 0,
          "gate": "c",
          "score": "1",
          "bonus": 1,
          "substitute_id": null,
          "substitute_no": null,
          "warning": null,
          "rider": {
            "id": 147,
            "name": "Andreas",
            "surname": "Jonsson"
          },
          "substitute": null
        },
        {
          "heat_id": 4954,
          "rider_id": 547,
          "rider_no": 3,
          "helmet": "yellow",
          "joker": 0,
          "gate": "b",
          "score": "3",
          "bonus": 0,
          "substitute_id": null,
          "substitute_no": null,
          "warning": null,
          "rider": {
            "id": 547,
            "name": "Dawid",
            "surname": "Lampart"
          },
          "substitute": null
        },
        {
          "heat_id": 4954,
          "rider_id": 59,
          "rider_no": 4,
          "helmet": "white",
          "joker": 0,
          "gate": "d",
          "score": "0",
          "bonus": 0,
          "substitute_id": null,
          "substitute_no": null,
          "warning": null,
          "rider": {
            "id": 59,
            "name": "Greg",
            "surname": "Hancock"
          },
          "substitute": null
        }
      ]
    },
    {
      "id": 4942,
      "canceled": 1,
      "no": 4,
      "restart_id": null,
      "home_heat_score": 0,
      "away_heat_score": 0,
      "home_match_score": null,
      "away_match_score": null,
      "results": [
        {
          "heat_id": 4942,
          "rider_id": 67,
          "rider_no": 13,
          "helmet": "red",
          "joker": 0,
          "gate": "d",
          "score": "U",
          "bonus": 0,
          "substitute_id": null,
          "substitute_no": null,
          "warning": null,
          "rider": {
            "id": 67,
            "name": "Piotr",
            "surname": "Protasiewicz"
          },
          "substitute": null
        },
        {
          "heat_id": 4942,
          "rider_id": 70,
          "rider_no": 15,
          "helmet": "blue",
          "joker": 0,
          "gate": "b",
          "score": null,
          "bonus": 0,
          "substitute_id": null,
          "substitute_no": null,
          "warning": null,
          "rider": {
            "id": 70,
            "name": "Krystian",
            "surname": "Pieszczek"
          },
          "substitute": null
        },
        {
          "heat_id": 4942,
          "rider_id": 88,
          "rider_no": 5,
          "helmet": "yellow",
          "joker": 0,
          "gate": "a",
          "score": null,
          "bonus": 0,
          "substitute_id": null,
          "substitute_no": null,
          "warning": null,
          "rider": {
            "id": 88,
            "name": "Peter",
            "surname": "Kildemand"
          },
          "substitute": null
        },
        {
          "heat_id": 4942,
          "rider_id": 124,
          "rider_no": 7,
          "helmet": "white",
          "joker": 0,
          "gate": "c",
          "score": "U",
          "bonus": 0,
          "substitute_id": null,
          "substitute_no": null,
          "warning": null,
          "rider": {
            "id": 124,
            "name": "Krystian",
            "surname": "Rempała"
          },
          "substitute": null
        }
      ]
    },
    {
      "id": 4955,
      "canceled": 0,
      "no": 4,
      "restart_id": 4942,
      "home_heat_score": 5,
      "away_heat_score": 1,
      "home_match_score": 14,
      "away_match_score": 10,
      "results": [
        {
          "heat_id": 4955,
          "rider_id": 67,
          "rider_no": 13,
          "helmet": "red",
          "joker": 0,
          "gate": "d",
          "score": "2",
          "bonus": 1,
          "substitute_id": null,
          "substitute_no": null,
          "warning": null,
          "rider": {
            "id": 67,
            "name": "Piotr",
            "surname": "Protasiewicz"
          },
          "substitute": null
        },
        {
          "heat_id": 4955,
          "rider_id": 70,
          "rider_no": 15,
          "helmet": "blue",
          "joker": 0,
          "gate": "b",
          "score": "3",
          "bonus": 0,
          "substitute_id": null,
          "substitute_no": null,
          "warning": null,
          "rider": {
            "id": 70,
            "name": "Krystian",
            "surname": "Pieszczek"
          },
          "substitute": null
        },
        {
          "heat_id": 4955,
          "rider_id": 88,
          "rider_no": 5,
          "helmet": "yellow",
          "joker": 0,
          "gate": "a",
          "score": "1",
          "bonus": 0,
          "substitute_id": null,
          "substitute_no": null,
          "warning": null,
          "rider": {
            "id": 88,
            "name": "Peter",
            "surname": "Kildemand"
          },
          "substitute": null
        },
        {
          "heat_id": 4955,
          "rider_id": 124,
          "rider_no": 7,
          "helmet": "white",
          "joker": 0,
          "gate": "c",
          "score": "0",
          "bonus": 0,
          "substitute_id": null,
          "substitute_no": null,
          "warning": null,
          "rider": {
            "id": 124,
            "name": "Krystian",
            "surname": "Rempała"
          },
          "substitute": null
        }
      ]
    },
    {
      "id": 4943,
      "canceled": 0,
      "no": 5,
      "restart_id": null,
      "home_heat_score": 4,
      "away_heat_score": 2,
      "home_match_score": 18,
      "away_match_score": 12,
      "results": [
        {
          "heat_id": 4943,
          "rider_id": 66,
          "rider_no": 11,
          "helmet": "red",
          "joker": 0,
          "gate": "c",
          "score": "3",
          "bonus": 0,
          "substitute_id": null,
          "substitute_no": null,
          "warning": null,
          "rider": {
            "id": 66,
            "name": "Grzegorz",
            "surname": "Walasek"
          },
          "substitute": null
        },
        {
          "heat_id": 4943,
          "rider_id": 147,
          "rider_no": 12,
          "helmet": "blue",
          "joker": 0,
          "gate": "a",
          "score": "1",
          "bonus": 0,
          "substitute_id": null,
          "substitute_no": null,
          "warning": null,
          "rider": {
            "id": 147,
            "name": "Andreas",
            "surname": "Jonsson"
          },
          "substitute": null
        },
        {
          "heat_id": 4943,
          "rider_id": 135,
          "rider_no": 1,
          "helmet": "yellow",
          "joker": 0,
          "gate": "b",
          "score": "2",
          "bonus": 0,
          "substitute_id": null,
          "substitute_no": null,
          "warning": null,
          "rider": {
            "id": 135,
            "name": "Peter",
            "surname": "Ljung"
          },
          "substitute": null
        },
        {
          "heat_id": 4943,
          "rider_id": 546,
          "rider_no": 2,
          "helmet": "white",
          "joker": 0,
          "gate": "d",
          "score": "0",
          "bonus": 0,
          "substitute_id": null,
          "substitute_no": null,
          "warning": null,
          "rider": {
            "id": 546,
            "name": "Mirosław",
            "surname": "Jabłoński"
          },
          "substitute": null
        }
      ]
    },
    {
      "id": 4944,
      "canceled": 0,
      "no": 6,
      "restart_id": null,
      "home_heat_score": 3,
      "away_heat_score": 3,
      "home_match_score": 21,
      "away_match_score": 15,
      "results": [
        {
          "heat_id": 4944,
          "rider_id": 67,
          "rider_no": 13,
          "helmet": "red",
          "joker": 0,
          "gate": "b",
          "score": "3",
          "bonus": 0,
          "substitute_id": null,
          "substitute_no": null,
          "warning": null,
          "rider": {
            "id": 67,
            "name": "Piotr",
            "surname": "Protasiewicz"
          },
          "substitute": null
        },
        {
          "heat_id": 4944,
          "rider_id": 80,
          "rider_no": 14,
          "helmet": "blue",
          "joker": 0,
          "gate": "d",
          "score": "0",
          "bonus": 0,
          "substitute_id": null,
          "substitute_no": null,
          "warning": null,
          "rider": {
            "id": 80,
            "name": "Alex",
            "surname": "Zgardziński"
          },
          "substitute": null
        },
        {
          "heat_id": 4944,
          "rider_id": 547,
          "rider_no": 3,
          "helmet": "yellow",
          "joker": 0,
          "gate": "a",
          "score": "1",
          "bonus": 1,
          "substitute_id": null,
          "substitute_no": null,
          "warning": null,
          "rider": {
            "id": 547,
            "name": "Dawid",
            "surname": "Lampart"
          },
          "substitute": null
        },
        {
          "heat_id": 4944,
          "rider_id": 59,
          "rider_no": 4,
          "helmet": "white",
          "joker": 0,
          "gate": "c",
          "score": "2",
          "bonus": 0,
          "substitute_id": null,
          "substitute_no": null,
          "warning": null,
          "rider": {
            "id": 59,
            "name": "Greg",
            "surname": "Hancock"
          },
          "substitute": null
        }
      ]
    },
    {
      "id": 4945,
      "canceled": 0,
      "no": 7,
      "restart_id": null,
      "home_heat_score": 4,
      "away_heat_score": 2,
      "home_match_score": 25,
      "away_match_score": 17,
      "results": [
        {
          "heat_id": 4945,
          "rider_id": 69,
          "rider_no": 9,
          "helmet": "red",
          "joker": 0,
          "gate": "a",
          "score": "3",
          "bonus": 0,
          "substitute_id": null,
          "substitute_no": null,
          "warning": null,
          "rider": {
            "id": 69,
            "name": "Jarosław",
            "surname": "Hampel"
          },
          "substitute": null
        },
        {
          "heat_id": 4945,
          "rider_id": 435,
          "rider_no": 10,
          "helmet": "blue",
          "joker": 0,
          "gate": "c",
          "score": "1",
          "bonus": 0,
          "substitute_id": null,
          "substitute_no": null,
          "warning": null,
          "rider": {
            "id": 435,
            "name": "Oleksandr",
            "surname": "Loktayev"
          },
          "substitute": null
        },
        {
          "heat_id": 4945,
          "rider_id": 88,
          "rider_no": 5,
          "helmet": "yellow",
          "joker": 0,
          "gate": "b",
          "score": "2",
          "bonus": 0,
          "substitute_id": null,
          "substitute_no": null,
          "warning": null,
          "rider": {
            "id": 88,
            "name": "Peter",
            "surname": "Kildemand"
          },
          "substitute": null
        },
        {
          "heat_id": 4945,
          "rider_id": 545,
          "rider_no": 6,
          "helmet": "white",
          "joker": 0,
          "gate": "d",
          "score": "0",
          "bonus": 0,
          "substitute_id": null,
          "substitute_no": null,
          "warning": null,
          "rider": {
            "id": 545,
            "name": "Artur",
            "surname": "Czaja"
          },
          "substitute": null
        }
      ]
    },
    {
      "id": 4946,
      "canceled": 0,
      "no": 8,
      "restart_id": null,
      "home_heat_score": 2,
      "away_heat_score": 4,
      "home_match_score": 27,
      "away_match_score": 21,
      "results": [
        {
          "heat_id": 4946,
          "rider_id": 67,
          "rider_no": 13,
          "helmet": "red",
          "joker": 0,
          "gate": "a",
          "score": "2",
          "bonus": 0,
          "substitute_id": null,
          "substitute_no": null,
          "warning": null,
          "rider": {
            "id": 67,
            "name": "Piotr",
            "surname": "Protasiewicz"
          },
          "substitute": null
        },
        {
          "heat_id": 4946,
          "rider_id": 70,
          "rider_no": 15,
          "helmet": "blue",
          "joker": 0,
          "gate": "c",
          "score": "0",
          "bonus": 0,
          "substitute_id": null,
          "substitute_no": null,
          "warning": null,
          "rider": {
            "id": 70,
            "name": "Krystian",
            "surname": "Pieszczek"
          },
          "substitute": null
        },
        {
          "heat_id": 4946,
          "rider_id": 135,
          "rider_no": 1,
          "helmet": "yellow",
          "joker": 0,
          "gate": "d",
          "score": "1",
          "bonus": 0,
          "substitute_id": null,
          "substitute_no": null,
          "warning": null,
          "rider": {
            "id": 135,
            "name": "Peter",
            "surname": "Ljung"
          },
          "substitute": null
        },
        {
          "heat_id": 4946,
          "rider_id": 546,
          "rider_no": 2,
          "helmet": "white",
          "joker": 0,
          "gate": "b",
          "score": "3",
          "bonus": 0,
          "substitute_id": 88,
          "substitute_no": 5,
          "warning": null,
          "rider": {
            "id": 546,
            "name": "Mirosław",
            "surname": "Jabłoński"
          },
          "substitute": {
            "id": 88,
            "name": "Peter",
            "surname": "Kildemand"
          }
        }
      ]
    },
    {
      "id": 4947,
      "canceled": 0,
      "no": 9,
      "restart_id": null,
      "home_heat_score": 5,
      "away_heat_score": 1,
      "home_match_score": 32,
      "away_match_score": 22,
      "results": [
        {
          "heat_id": 4947,
          "rider_id": 69,
          "rider_no": 9,
          "helmet": "red",
          "joker": 0,
          "gate": "d",
          "score": "3",
          "bonus": 0,
          "substitute_id": null,
          "substitute_no": null,
          "warning": null,
          "rider": {
            "id": 69,
            "name": "Jarosław",
            "surname": "Hampel"
          },
          "substitute": null
        },
        {
          "heat_id": 4947,
          "rider_id": 435,
          "rider_no": 10,
          "helmet": "blue",
          "joker": 0,
          "gate": "b",
          "score": "2",
          "bonus": 1,
          "substitute_id": null,
          "substitute_no": null,
          "warning": null,
          "rider": {
            "id": 435,
            "name": "Oleksandr",
            "surname": "Loktayev"
          },
          "substitute": null
        },
        {
          "heat_id": 4947,
          "rider_id": 547,
          "rider_no": 3,
          "helmet": "yellow",
          "joker": 0,
          "gate": "c",
          "score": "1",
          "bonus": 0,
          "substitute_id": null,
          "substitute_no": null,
          "warning": null,
          "rider": {
            "id": 547,
            "name": "Dawid",
            "surname": "Lampart"
          },
          "substitute": null
        },
        {
          "heat_id": 4947,
          "rider_id": 59,
          "rider_no": 4,
          "helmet": "white",
          "joker": 0,
          "gate": "a",
          "score": "0",
          "bonus": 0,
          "substitute_id": null,
          "substitute_no": null,
          "warning": null,
          "rider": {
            "id": 59,
            "name": "Greg",
            "surname": "Hancock"
          },
          "substitute": null
        }
      ]
    },
    {
      "id": 4948,
      "canceled": 0,
      "no": 10,
      "restart_id": null,
      "home_heat_score": 3,
      "away_heat_score": 3,
      "home_match_score": 35,
      "away_match_score": 25,
      "results": [
        {
          "heat_id": 4948,
          "rider_id": 66,
          "rider_no": 11,
          "helmet": "red",
          "joker": 0,
          "gate": "b",
          "score": "2",
          "bonus": 0,
          "substitute_id": null,
          "substitute_no": null,
          "warning": null,
          "rider": {
            "id": 66,
            "name": "Grzegorz",
            "surname": "Walasek"
          },
          "substitute": null
        },
        {
          "heat_id": 4948,
          "rider_id": 147,
          "rider_no": 12,
          "helmet": "blue",
          "joker": 0,
          "gate": "d",
          "score": "1",
          "bonus": 1,
          "substitute_id": null,
          "substitute_no": null,
          "warning": null,
          "rider": {
            "id": 147,
            "name": "Andreas",
            "surname": "Jonsson"
          },
          "substitute": null
        },
        {
          "heat_id": 4948,
          "rider_id": 88,
          "rider_no": 5,
          "helmet": "yellow",
          "joker": 0,
          "gate": "c",
          "score": "3",
          "bonus": 0,
          "substitute_id": null,
          "substitute_no": null,
          "warning": null,
          "rider": {
            "id": 88,
            "name": "Peter",
            "surname": "Kildemand"
          },
          "substitute": null
        },
        {
          "heat_id": 4948,
          "rider_id": 124,
          "rider_no": 7,
          "helmet": "white",
          "joker": 0,
          "gate": "a",
          "score": "0",
          "bonus": 0,
          "substitute_id": 545,
          "substitute_no": 6,
          "warning": null,
          "rider": {
            "id": 124,
            "name": "Krystian",
            "surname": "Rempała"
          },
          "substitute": {
            "id": 545,
            "name": "Artur",
            "surname": "Czaja"
          }
        }
      ]
    },
    {
      "id": 4949,
      "canceled": 0,
      "no": 11,
      "restart_id": null,
      "home_heat_score": 5,
      "away_heat_score": 1,
      "home_match_score": 40,
      "away_match_score": 26,
      "results": [
        {
          "heat_id": 4949,
          "rider_id": 67,
          "rider_no": 13,
          "helmet": "red",
          "joker": 0,
          "gate": "c",
          "score": "3",
          "bonus": 0,
          "substitute_id": null,
          "substitute_no": null,
          "warning": null,
          "rider": {
            "id": 67,
            "name": "Piotr",
            "surname": "Protasiewicz"
          },
          "substitute": null
        },
        {
          "heat_id": 4949,
          "rider_id": 435,
          "rider_no": 10,
          "helmet": "blue",
          "joker": 0,
          "gate": "a",
          "score": "2",
          "bonus": 1,
          "substitute_id": null,
          "substitute_no": null,
          "warning": null,
          "rider": {
            "id": 435,
            "name": "Oleksandr",
            "surname": "Loktayev"
          },
          "substitute": null
        },
        {
          "heat_id": 4949,
          "rider_id": 547,
          "rider_no": 3,
          "helmet": "yellow",
          "joker": 0,
          "gate": "d",
          "score": "0",
          "bonus": 0,
          "substitute_id": null,
          "substitute_no": null,
          "warning": null,
          "rider": {
            "id": 547,
            "name": "Dawid",
            "surname": "Lampart"
          },
          "substitute": null
        },
        {
          "heat_id": 4949,
          "rider_id": 546,
          "rider_no": 2,
          "helmet": "white",
          "joker": 0,
          "gate": "b",
          "score": "1",
          "bonus": 0,
          "substitute_id": null,
          "substitute_no": null,
          "warning": null,
          "rider": {
            "id": 546,
            "name": "Mirosław",
            "surname": "Jabłoński"
          },
          "substitute": null
        }
      ]
    },
    {
      "id": 4950,
      "canceled": 0,
      "no": 12,
      "restart_id": null,
      "home_heat_score": 2,
      "away_heat_score": 4,
      "home_match_score": 42,
      "away_match_score": 30,
      "results": [
        {
          "heat_id": 4950,
          "rider_id": 66,
          "rider_no": 11,
          "helmet": "red",
          "joker": 0,
          "gate": "d",
          "score": "2",
          "bonus": 0,
          "substitute_id": null,
          "substitute_no": null,
          "warning": null,
          "rider": {
            "id": 66,
            "name": "Grzegorz",
            "surname": "Walasek"
          },
          "substitute": null
        },
        {
          "heat_id": 4950,
          "rider_id": 80,
          "rider_no": 14,
          "helmet": "blue",
          "joker": 0,
          "gate": "b",
          "score": "0",
          "bonus": 0,
          "substitute_id": null,
          "substitute_no": null,
          "warning": null,
          "rider": {
            "id": 80,
            "name": "Alex",
            "surname": "Zgardziński"
          },
          "substitute": null
        },
        {
          "heat_id": 4950,
          "rider_id": 135,
          "rider_no": 1,
          "helmet": "yellow",
          "joker": 0,
          "gate": "c",
          "score": "1",
          "bonus": 0,
          "substitute_id": null,
          "substitute_no": null,
          "warning": null,
          "rider": {
            "id": 135,
            "name": "Peter",
            "surname": "Ljung"
          },
          "substitute": null
        },
        {
          "heat_id": 4950,
          "rider_id": 545,
          "rider_no": 6,
          "helmet": "white",
          "joker": 0,
          "gate": "a",
          "score": "3",
          "bonus": 0,
          "substitute_id": null,
          "substitute_no": null,
          "warning": null,
          "rider": {
            "id": 545,
            "name": "Artur",
            "surname": "Czaja"
          },
          "substitute": null
        }
      ]
    },
    {
      "id": 4951,
      "canceled": 0,
      "no": 13,
      "restart_id": null,
      "home_heat_score": 2,
      "away_heat_score": 4,
      "home_match_score": 44,
      "away_match_score": 34,
      "results": [
        {
          "heat_id": 4951,
          "rider_id": 69,
          "rider_no": 9,
          "helmet": "red",
          "joker": 0,
          "gate": "c",
          "score": "2",
          "bonus": 0,
          "substitute_id": null,
          "substitute_no": null,
          "warning": null,
          "rider": {
            "id": 69,
            "name": "Jarosław",
            "surname": "Hampel"
          },
          "substitute": null
        },
        {
          "heat_id": 4951,
          "rider_id": 147,
          "rider_no": 12,
          "helmet": "blue",
          "joker": 0,
          "gate": "a",
          "score": "0",
          "bonus": 0,
          "substitute_id": null,
          "substitute_no": null,
          "warning": null,
          "rider": {
            "id": 147,
            "name": "Andreas",
            "surname": "Jonsson"
          },
          "substitute": null
        },
        {
          "heat_id": 4951,
          "rider_id": 88,
          "rider_no": 5,
          "helmet": "yellow",
          "joker": 0,
          "gate": "d",
          "score": "1",
          "bonus": 0,
          "substitute_id": null,
          "substitute_no": null,
          "warning": null,
          "rider": {
            "id": 88,
            "name": "Peter",
            "surname": "Kildemand"
          },
          "substitute": null
        },
        {
          "heat_id": 4951,
          "rider_id": 59,
          "rider_no": 4,
          "helmet": "white",
          "joker": 0,
          "gate": "b",
          "score": "3",
          "bonus": 0,
          "substitute_id": null,
          "substitute_no": null,
          "warning": null,
          "rider": {
            "id": 59,
            "name": "Greg",
            "surname": "Hancock"
          },
          "substitute": null
        }
      ]
    },
    {
      "id": 4952,
      "canceled": 1,
      "no": 14,
      "restart_id": null,
      "home_heat_score": 0,
      "away_heat_score": 0,
      "home_match_score": null,
      "away_match_score": null,
      "results": [
        {
          "heat_id": 4952,
          "rider_id": 435,
          "rider_no": 10,
          "helmet": "red",
          "joker": 0,
          "gate": "b",
          "score": null,
          "bonus": 0,
          "substitute_id": null,
          "substitute_no": null,
          "warning": null,
          "rider": {
            "id": 435,
            "name": "Oleksandr",
            "surname": "Loktayev"
          },
          "substitute": null
        },
        {
          "heat_id": 4952,
          "rider_id": 66,
          "rider_no": 11,
          "helmet": "blue",
          "joker": 0,
          "gate": "d",
          "score": null,
          "bonus": 0,
          "substitute_id": null,
          "substitute_no": null,
          "warning": null,
          "rider": {
            "id": 66,
            "name": "Grzegorz",
            "surname": "Walasek"
          },
          "substitute": null
        },
        {
          "heat_id": 4952,
          "rider_id": 546,
          "rider_no": 2,
          "helmet": "yellow",
          "joker": 0,
          "gate": "a",
          "score": null,
          "bonus": 0,
          "substitute_id": 545,
          "substitute_no": 6,
          "warning": null,
          "rider": {
            "id": 546,
            "name": "Mirosław",
            "surname": "Jabłoński"
          },
          "substitute": {
            "id": 545,
            "name": "Artur",
            "surname": "Czaja"
          }
        },
        {
          "heat_id": 4952,
          "rider_id": 59,
          "rider_no": 4,
          "helmet": "white",
          "joker": 0,
          "gate": "c",
          "score": null,
          "bonus": 0,
          "substitute_id": null,
          "substitute_no": null,
          "warning": null,
          "rider": {
            "id": 59,
            "name": "Greg",
            "surname": "Hancock"
          },
          "substitute": null
        }
      ]
    },
    {
      "id": 4956,
      "canceled": 1,
      "no": 14,
      "restart_id": 4952,
      "home_heat_score": 0,
      "away_heat_score": 0,
      "home_match_score": null,
      "away_match_score": null,
      "results": [
        {
          "heat_id": 4956,
          "rider_id": 435,
          "rider_no": 10,
          "helmet": "red",
          "joker": 0,
          "gate": "b",
          "score": null,
          "bonus": 0,
          "substitute_id": null,
          "substitute_no": null,
          "warning": null,
          "rider": {
            "id": 435,
            "name": "Oleksandr",
            "surname": "Loktayev"
          },
          "substitute": null
        },
        {
          "heat_id": 4956,
          "rider_id": 66,
          "rider_no": 11,
          "helmet": "blue",
          "joker": 0,
          "gate": "d",
          "score": null,
          "bonus": 0,
          "substitute_id": null,
          "substitute_no": null,
          "warning": null,
          "rider": {
            "id": 66,
            "name": "Grzegorz",
            "surname": "Walasek"
          },
          "substitute": null
        },
        {
          "heat_id": 4956,
          "rider_id": 546,
          "rider_no": 2,
          "helmet": "yellow",
          "joker": 0,
          "gate": "a",
          "score": null,
          "bonus": 0,
          "substitute_id": 545,
          "substitute_no": 6,
          "warning": null,
          "rider": {
            "id": 546,
            "name": "Mirosław",
            "surname": "Jabłoński"
          },
          "substitute": {
            "id": 545,
            "name": "Artur",
            "surname": "Czaja"
          }
        },
        {
          "heat_id": 4956,
          "rider_id": 59,
          "rider_no": 4,
          "helmet": "white",
          "joker": 0,
          "gate": "c",
          "score": null,
          "bonus": 0,
          "substitute_id": null,
          "substitute_no": null,
          "warning": null,
          "rider": {
            "id": 59,
            "name": "Greg",
            "surname": "Hancock"
          },
          "substitute": null
        }
      ]
    },
    {
      "id": 4957,
      "canceled": 0,
      "no": 14,
      "restart_id": 4956,
      "home_heat_score": 4,
      "away_heat_score": 2,
      "home_match_score": 48,
      "away_match_score": 36,
      "results": [
        {
          "heat_id": 4957,
          "rider_id": 435,
          "rider_no": 10,
          "helmet": "red",
          "joker": 0,
          "gate": "b",
          "score": "3",
          "bonus": 0,
          "substitute_id": null,
          "substitute_no": null,
          "warning": null,
          "rider": {
            "id": 435,
            "name": "Oleksandr",
            "surname": "Loktayev"
          },
          "substitute": null
        },
        {
          "heat_id": 4957,
          "rider_id": 66,
          "rider_no": 11,
          "helmet": "blue",
          "joker": 0,
          "gate": "d",
          "score": "1",
          "bonus": 0,
          "substitute_id": null,
          "substitute_no": null,
          "warning": null,
          "rider": {
            "id": 66,
            "name": "Grzegorz",
            "surname": "Walasek"
          },
          "substitute": null
        },
        {
          "heat_id": 4957,
          "rider_id": 546,
          "rider_no": 2,
          "helmet": "yellow",
          "joker": 0,
          "gate": "a",
          "score": "0",
          "bonus": 0,
          "substitute_id": 545,
          "substitute_no": 6,
          "warning": null,
          "rider": {
            "id": 546,
            "name": "Mirosław",
            "surname": "Jabłoński"
          },
          "substitute": {
            "id": 545,
            "name": "Artur",
            "surname": "Czaja"
          }
        },
        {
          "heat_id": 4957,
          "rider_id": 59,
          "rider_no": 4,
          "helmet": "white",
          "joker": 0,
          "gate": "c",
          "score": "2",
          "bonus": 0,
          "substitute_id": null,
          "substitute_no": null,
          "warning": null,
          "rider": {
            "id": 59,
            "name": "Greg",
            "surname": "Hancock"
          },
          "substitute": null
        }
      ]
    },
    {
      "id": 4953,
      "canceled": 0,
      "no": 15,
      "restart_id": null,
      "home_heat_score": 2,
      "away_heat_score": 4,
      "home_match_score": 50,
      "away_match_score": 40,
      "results": [
        {
          "heat_id": 4953,
          "rider_id": 69,
          "rider_no": 9,
          "helmet": "red",
          "joker": 0,
          "gate": "a",
          "score": "2",
          "bonus": 0,
          "substitute_id": null,
          "substitute_no": null,
          "warning": null,
          "rider": {
            "id": 69,
            "name": "Jarosław",
            "surname": "Hampel"
          },
          "substitute": null
        },
        {
          "heat_id": 4953,
          "rider_id": 67,
          "rider_no": 13,
          "helmet": "blue",
          "joker": 0,
          "gate": "c",
          "score": "0",
          "bonus": 0,
          "substitute_id": null,
          "substitute_no": null,
          "warning": null,
          "rider": {
            "id": 67,
            "name": "Piotr",
            "surname": "Protasiewicz"
          },
          "substitute": null
        },
        {
          "heat_id": 4953,
          "rider_id": 135,
          "rider_no": 1,
          "helmet": "yellow",
          "joker": 0,
          "gate": "b",
          "score": "3",
          "bonus": 0,
          "substitute_id": 59,
          "substitute_no": 4,
          "warning": null,
          "rider": {
            "id": 135,
            "name": "Peter",
            "surname": "Ljung"
          },
          "substitute": {
            "id": 59,
            "name": "Greg",
            "surname": "Hancock"
          }
        },
        {
          "heat_id": 4953,
          "rider_id": 88,
          "rider_no": 5,
          "helmet": "white",
          "joker": 0,
          "gate": "d",
          "score": "1",
          "bonus": 0,
          "substitute_id": null,
          "substitute_no": null,
          "warning": null,
          "rider": {
            "id": 88,
            "name": "Peter",
            "surname": "Kildemand"
          },
          "substitute": null
        }
      ]
    }
  ],
  "comments": [],
  "lineups": [
    {
      "id": 3739,
      "protocol_id": 398,
      "card_id": 421,
      "no": 9,
      "type": 1,
      "team_id": 5,
      "user_id": 69,
      "rider_replacement": 0,
      "average_order": null,
      "warning_heat_order": null,
      "position": null,
      "status": null,
      "team_no": 1,
      "points": 13,
      "points_regular": 13,
      "bonuses": 0,
      "bonuses_regular": 0,
      "starts": 5,
      "starts_regular": 5,
      "starts_additional": 0,
      "rider": {
        "id": 69,
        "name": "Jarosław",
        "surname": "Hampel"
      },
      "scores_regular": [
        {
          "score": "3",
          "joker": 0,
          "bonus": 0,
          "lineup_id": 3739
        },
        {
          "score": "3",
          "joker": 0,
          "bonus": 0,
          "lineup_id": 3739
        },
        {
          "score": "3",
          "joker": 0,
          "bonus": 0,
          "lineup_id": 3739
        },
        {
          "score": "2",
          "joker": 0,
          "bonus": 0,
          "lineup_id": 3739
        },
        {
          "score": "2",
          "joker": 0,
          "bonus": 0,
          "lineup_id": 3739
        }
      ],
      "scores_additional": []
    },
    {
      "id": 3740,
      "protocol_id": 398,
      "card_id": 421,
      "no": 10,
      "type": 1,
      "team_id": 5,
      "user_id": 435,
      "rider_replacement": 0,
      "average_order": null,
      "warning_heat_order": null,
      "position": null,
      "status": null,
      "team_no": 2,
      "points": 8,
      "points_regular": 8,
      "bonuses": 2,
      "bonuses_regular": 2,
      "starts": 5,
      "starts_regular": 5,
      "starts_additional": 0,
      "rider": {
        "id": 435,
        "name": "Oleksandr",
        "surname": "Loktayev"
      },
      "scores_regular": [
        {
          "score": "0",
          "joker": 0,
          "bonus": 0,
          "lineup_id": 3740
        },
        {
          "score": "1",
          "joker": 0,
          "bonus": 0,
          "lineup_id": 3740
        },
        {
          "score": "2",
          "joker": 0,
          "bonus": 1,
          "lineup_id": 3740
        },
        {
          "score": "2",
          "joker": 0,
          "bonus": 1,
          "lineup_id": 3740
        },
        {
          "score": "3",
          "joker": 0,
          "bonus": 0,
          "lineup_id": 3740
        }
      ],
      "scores_additional": []
    },
    {
      "id": 3741,
      "protocol_id": 398,
      "card_id": 421,
      "no": 11,
      "type": 1,
      "team_id": 5,
      "user_id": 66,
      "rider_replacement": 0,
      "average_order": null,
      "warning_heat_order": null,
      "position": null,
      "status": null,
      "team_no": 3,
      "points": 10,
      "points_regular": 10,
      "bonuses": 0,
      "bonuses_regular": 0,
      "starts": 5,
      "starts_regular": 5,
      "starts_additional": 0,
      "rider": {
        "id": 66,
        "name": "Grzegorz",
        "surname": "Walasek"
      },
      "scores_regular": [
        {
          "score": "2",
          "joker": 0,
          "bonus": 0,
          "lineup_id": 3741
        },
        {
          "score": "3",
          "joker": 0,
          "bonus": 0,
          "lineup_id": 3741
        },
        {
          "score": "2",
          "joker": 0,
          "bonus": 0,
          "lineup_id": 3741
        },
        {
          "score": "2",
          "joker": 0,
          "bonus": 0,
          "lineup_id": 3741
        },
        {
          "score": "1",
          "joker": 0,
          "bonus": 0,
          "lineup_id": 3741
        }
      ],
      "scores_additional": []
    },
    {
      "id": 3742,
      "protocol_id": 398,
      "card_id": 421,
      "no": 12,
      "type": 1,
      "team_id": 5,
      "user_id": 147,
      "rider_replacement": 0,
      "average_order": null,
      "warning_heat_order": null,
      "position": null,
      "status": null,
      "team_no": 4,
      "points": 3,
      "points_regular": 3,
      "bonuses": 2,
      "bonuses_regular": 2,
      "starts": 4,
      "starts_regular": 4,
      "starts_additional": 0,
      "rider": {
        "id": 147,
        "name": "Andreas",
        "surname": "Jonsson"
      },
      "scores_regular": [
        {
          "score": "1",
          "joker": 0,
          "bonus": 1,
          "lineup_id": 3742
        },
        {
          "score": "1",
          "joker": 0,
          "bonus": 0,
          "lineup_id": 3742
        },
        {
          "score": "1",
          "joker": 0,
          "bonus": 1,
          "lineup_id": 3742
        },
        {
          "score": "0",
          "joker": 0,
          "bonus": 0,
          "lineup_id": 3742
        }
      ],
      "scores_additional": []
    },
    {
      "id": 3743,
      "protocol_id": 398,
      "card_id": 421,
      "no": 13,
      "type": 1,
      "team_id": 5,
      "user_id": 67,
      "rider_replacement": 0,
      "average_order": null,
      "warning_heat_order": null,
      "position": null,
      "status": null,
      "team_no": 5,
      "points": 10,
      "points_regular": 10,
      "bonuses": 1,
      "bonuses_regular": 1,
      "starts": 5,
      "starts_regular": 5,
      "starts_additional": 0,
      "rider": {
        "id": 67,
        "name": "Piotr",
        "surname": "Protasiewicz"
      },
      "scores_regular": [
        {
          "score": "2",
          "joker": 0,
          "bonus": 1,
          "lineup_id": 3743
        },
        {
          "score": "3",
          "joker": 0,
          "bonus": 0,
          "lineup_id": 3743
        },
        {
          "score": "2",
          "joker": 0,
          "bonus": 0,
          "lineup_id": 3743
        },
        {
          "score": "3",
          "joker": 0,
          "bonus": 0,
          "lineup_id": 3743
        },
        {
          "score": "0",
          "joker": 0,
          "bonus": 0,
          "lineup_id": 3743
        }
      ],
      "scores_additional": []
    },
    {
      "id": 3744,
      "protocol_id": 398,
      "card_id": 421,
      "no": 14,
      "type": 1,
      "team_id": 5,
      "user_id": 80,
      "rider_replacement": 0,
      "average_order": null,
      "warning_heat_order": null,
      "position": null,
      "status": null,
      "team_no": 6,
      "points": 2,
      "points_regular": 2,
      "bonuses": 0,
      "bonuses_regular": 0,
      "starts": 3,
      "starts_regular": 3,
      "starts_additional": 0,
      "rider": {
        "id": 80,
        "name": "Alex",
        "surname": "Zgardziński"
      },
      "scores_regular": [
        {
          "score": "2",
          "joker": 0,
          "bonus": 0,
          "lineup_id": 3744
        },
        {
          "score": "0",
          "joker": 0,
          "bonus": 0,
          "lineup_id": 3744
        },
        {
          "score": "0",
          "joker": 0,
          "bonus": 0,
          "lineup_id": 3744
        }
      ],
      "scores_additional": []
    },
    {
      "id": 3745,
      "protocol_id": 398,
      "card_id": 421,
      "no": 15,
      "type": 1,
      "team_id": 5,
      "user_id": 70,
      "rider_replacement": 0,
      "average_order": null,
      "warning_heat_order": null,
      "position": null,
      "status": null,
      "team_no": 7,
      "points": 4,
      "points_regular": 4,
      "bonuses": 1,
      "bonuses_regular": 1,
      "starts": 3,
      "starts_regular": 3,
      "starts_additional": 0,
      "rider": {
        "id": 70,
        "name": "Krystian",
        "surname": "Pieszczek"
      },
      "scores_regular": [
        {
          "score": "1",
          "joker": 0,
          "bonus": 1,
          "lineup_id": 3745
        },
        {
          "score": "3",
          "joker": 0,
          "bonus": 0,
          "lineup_id": 3745
        },
        {
          "score": "0",
          "joker": 0,
          "bonus": 0,
          "lineup_id": 3745
        }
      ],
      "scores_additional": []
    },
    {
      "id": 3732,
      "protocol_id": 398,
      "card_id": 421,
      "no": 1,
      "type": 2,
      "team_id": 10,
      "user_id": 135,
      "rider_replacement": 0,
      "average_order": null,
      "warning_heat_order": null,
      "position": null,
      "status": null,
      "team_no": 1,
      "points": 6,
      "points_regular": 6,
      "bonuses": 0,
      "bonuses_regular": 0,
      "starts": 4,
      "starts_regular": 4,
      "starts_additional": 0,
      "rider": {
        "id": 135,
        "name": "Peter",
        "surname": "Ljung"
      },
      "scores_regular": [
        {
          "score": "2",
          "joker": 0,
          "bonus": 0,
          "lineup_id": 3732
        },
        {
          "score": "2",
          "joker": 0,
          "bonus": 0,
          "lineup_id": 3732
        },
        {
          "score": "1",
          "joker": 0,
          "bonus": 0,
          "lineup_id": 3732
        },
        {
          "score": "1",
          "joker": 0,
          "bonus": 0,
          "lineup_id": 3732
        },
        {
          "score": "-",
          "joker": 0,
          "bonus": 0,
          "lineup_id": 3732
        }
      ],
      "scores_additional": []
    },
    {
      "id": 3733,
      "protocol_id": 398,
      "card_id": 421,
      "no": 2,
      "type": 2,
      "team_id": 10,
      "user_id": 546,
      "rider_replacement": 0,
      "average_order": null,
      "warning_heat_order": null,
      "position": null,
      "status": null,
      "team_no": 2,
      "points": 2,
      "points_regular": 2,
      "bonuses": 1,
      "bonuses_regular": 1,
      "starts": 3,
      "starts_regular": 3,
      "starts_additional": 0,
      "rider": {
        "id": 546,
        "name": "Mirosław",
        "surname": "Jabłoński"
      },
      "scores_regular": [
        {
          "score": "1",
          "joker": 0,
          "bonus": 1,
          "lineup_id": 3733
        },
        {
          "score": "0",
          "joker": 0,
          "bonus": 0,
          "lineup_id": 3733
        },
        {
          "score": "-",
          "joker": 0,
          "bonus": 0,
          "lineup_id": 3733
        },
        {
          "score": "1",
          "joker": 0,
          "bonus": 0,
          "lineup_id": 3733
        },
        {
          "score": "-",
          "joker": 0,
          "bonus": 0,
          "lineup_id": 3733
        }
      ],
      "scores_additional": []
    },
    {
      "id": 3734,
      "protocol_id": 398,
      "card_id": 421,
      "no": 3,
      "type": 2,
      "team_id": 10,
      "user_id": 547,
      "rider_replacement": 0,
      "average_order": null,
      "warning_heat_order": null,
      "position": null,
      "status": null,
      "team_no": 3,
      "points": 5,
      "points_regular": 5,
      "bonuses": 1,
      "bonuses_regular": 1,
      "starts": 4,
      "starts_regular": 4,
      "starts_additional": 0,
      "rider": {
        "id": 547,
        "name": "Dawid",
        "surname": "Lampart"
      },
      "scores_regular": [
        {
          "score": "3",
          "joker": 0,
          "bonus": 0,
          "lineup_id": 3734
        },
        {
          "score": "1",
          "joker": 0,
          "bonus": 1,
          "lineup_id": 3734
        },
        {
          "score": "1",
          "joker": 0,
          "bonus": 0,
          "lineup_id": 3734
        },
        {
          "score": "0",
          "joker": 0,
          "bonus": 0,
          "lineup_id": 3734
        }
      ],
      "scores_additional": []
    },
    {
      "id": 3735,
      "protocol_id": 398,
      "card_id": 421,
      "no": 4,
      "type": 2,
      "team_id": 10,
      "user_id": 59,
      "rider_replacement": 0,
      "average_order": null,
      "warning_heat_order": null,
      "position": null,
      "status": null,
      "team_no": 4,
      "points": 10,
      "points_regular": 10,
      "bonuses": 0,
      "bonuses_regular": 0,
      "starts": 6,
      "starts_regular": 6,
      "starts_additional": 0,
      "rider": {
        "id": 59,
        "name": "Greg",
        "surname": "Hancock"
      },
      "scores_regular": [
        {
          "score": "0",
          "joker": 0,
          "bonus": 0,
          "lineup_id": 3735
        },
        {
          "score": "2",
          "joker": 0,
          "bonus": 0,
          "lineup_id": 3735
        },
        {
          "score": "0",
          "joker": 0,
          "bonus": 0,
          "lineup_id": 3735
        },
        {
          "score": "3",
          "joker": 0,
          "bonus": 0,
          "lineup_id": 3735
        },
        {
          "score": "2",
          "joker": 0,
          "bonus": 0,
          "lineup_id": 3735
        },
        {
          "score": "3",
          "joker": 0,
          "bonus": 0,
          "lineup_id": 3735
        }
      ],
      "scores_additional": []
    },
    {
      "id": 3736,
      "protocol_id": 398,
      "card_id": 421,
      "no": 5,
      "type": 2,
      "team_id": 10,
      "user_id": 88,
      "rider_replacement": 0,
      "average_order": null,
      "warning_heat_order": null,
      "position": null,
      "status": null,
      "team_no": 5,
      "points": 11,
      "points_regular": 11,
      "bonuses": 0,
      "bonuses_regular": 0,
      "starts": 6,
      "starts_regular": 6,
      "starts_additional": 0,
      "rider": {
        "id": 88,
        "name": "Peter",
        "surname": "Kildemand"
      },
      "scores_regular": [
        {
          "score": "1",
          "joker": 0,
          "bonus": 0,
          "lineup_id": 3736
        },
        {
          "score": "2",
          "joker": 0,
          "bonus": 0,
          "lineup_id": 3736
        },
        {
          "score": "3",
          "joker": 0,
          "bonus": 0,
          "lineup_id": 3736
        },
        {
          "score": "3",
          "joker": 0,
          "bonus": 0,
          "lineup_id": 3736
        },
        {
          "score": "1",
          "joker": 0,
          "bonus": 0,
          "lineup_id": 3736
        },
        {
          "score": "1",
          "joker": 0,
          "bonus": 0,
          "lineup_id": 3736
        }
      ],
      "scores_additional": []
    },
    {
      "id": 3737,
      "protocol_id": 398,
      "card_id": 421,
      "no": 6,
      "type": 2,
      "team_id": 10,
      "user_id": 545,
      "rider_replacement": 0,
      "average_order": null,
      "warning_heat_order": null,
      "position": null,
      "status": null,
      "team_no": 6,
      "points": 6,
      "points_regular": 6,
      "bonuses": 0,
      "bonuses_regular": 0,
      "starts": 5,
      "starts_regular": 5,
      "starts_additional": 0,
      "rider": {
        "id": 545,
        "name": "Artur",
        "surname": "Czaja"
      },
      "scores_regular": [
        {
          "score": "3",
          "joker": 0,
          "bonus": 0,
          "lineup_id": 3737
        },
        {
          "score": "0",
          "joker": 0,
          "bonus": 0,
          "lineup_id": 3737
        },
        {
          "score": "0",
          "joker": 0,
          "bonus": 0,
          "lineup_id": 3737
        },
        {
          "score": "3",
          "joker": 0,
          "bonus": 0,
          "lineup_id": 3737
        },
        {
          "score": "0",
          "joker": 0,
          "bonus": 0,
          "lineup_id": 3737
        }
      ],
      "scores_additional": []
    },
    {
      "id": 3738,
      "protocol_id": 398,
      "card_id": 421,
      "no": 7,
      "type": 2,
      "team_id": 10,
      "user_id": 124,
      "rider_replacement": 0,
      "average_order": null,
      "warning_heat_order": null,
      "position": null,
      "status": null,
      "team_no": 7,
      "points": 0,
      "points_regular": 0,
      "bonuses": 0,
      "bonuses_regular": 0,
      "starts": 2,
      "starts_regular": 2,
      "starts_additional": 0,
      "rider": {
        "id": 124,
        "name": "Krystian",
        "surname": "Rempała"
      },
      "scores_regular": [
        {
          "score": "0",
          "joker": 0,
          "bonus": 0,
          "lineup_id": 3738
        },
        {
          "score": "0",
          "joker": 0,
          "bonus": 0,
          "lineup_id": 3738
        },
        {
          "score": "-",
          "joker": 0,
          "bonus": 0,
          "lineup_id": 3738
        }
      ],
      "scores_additional": []
    }
  ],
  "telemetry": [
    {
      "general": {
        "rider_id": 135,
        "no": 1,
        "name": "Peter",
        "surname": "Ljung",
        "team_shortcut": "RZE",
        "best_reaction": null,
        "best_reaction_heat_no": null,
        "best_time": null,
        "best_time_heat_no": null,
        "best_max_speed": null,
        "best_max_speed_heat_no": null
      },
      "details": []
    },
    {
      "general": {
        "rider_id": 546,
        "no": 2,
        "name": "Mirosław",
        "surname": "Jabłoński",
        "team_shortcut": "RZE",
        "best_reaction": null,
        "best_reaction_heat_no": null,
        "best_time": null,
        "best_time_heat_no": null,
        "best_max_speed": null,
        "best_max_speed_heat_no": null
      },
      "details": []
    },
    {
      "general": {
        "rider_id": 547,
        "no": 3,
        "name": "Dawid",
        "surname": "Lampart",
        "team_shortcut": "RZE",
        "best_reaction": null,
        "best_reaction_heat_no": null,
        "best_time": null,
        "best_time_heat_no": null,
        "best_max_speed": null,
        "best_max_speed_heat_no": null
      },
      "details": []
    },
    {
      "general": {
        "rider_id": 59,
        "no": 4,
        "name": "Greg",
        "surname": "Hancock",
        "team_shortcut": "RZE",
        "best_reaction": null,
        "best_reaction_heat_no": null,
        "best_time": null,
        "best_time_heat_no": null,
        "best_max_speed": null,
        "best_max_speed_heat_no": null
      },
      "details": []
    },
    {
      "general": {
        "rider_id": 88,
        "no": 5,
        "name": "Peter",
        "surname": "Kildemand",
        "team_shortcut": "RZE",
        "best_reaction": null,
        "best_reaction_heat_no": null,
        "best_time": null,
        "best_time_heat_no": null,
        "best_max_speed": null,
        "best_max_speed_heat_no": null
      },
      "details": []
    },
    {
      "general": {
        "rider_id": 545,
        "no": 6,
        "name": "Artur",
        "surname": "Czaja",
        "team_shortcut": "RZE",
        "best_reaction": null,
        "best_reaction_heat_no": null,
        "best_time": null,
        "best_time_heat_no": null,
        "best_max_speed": null,
        "best_max_speed_heat_no": null
      },
      "details": []
    },
    {
      "general": {
        "rider_id": 124,
        "no": 7,
        "name": "Krystian",
        "surname": "Rempała",
        "team_shortcut": "RZE",
        "best_reaction": null,
        "best_reaction_heat_no": null,
        "best_time": null,
        "best_time_heat_no": null,
        "best_max_speed": null,
        "best_max_speed_heat_no": null
      },
      "details": []
    },
    {
      "general": {
        "rider_id": 69,
        "no": 9,
        "name": "Jarosław",
        "surname": "Hampel",
        "team_shortcut": "ZIE",
        "best_reaction": null,
        "best_reaction_heat_no": null,
        "best_time": null,
        "best_time_heat_no": null,
        "best_max_speed": null,
        "best_max_speed_heat_no": null
      },
      "details": []
    },
    {
      "general": {
        "rider_id": 435,
        "no": 10,
        "name": "Oleksandr",
        "surname": "Loktayev",
        "team_shortcut": "ZIE",
        "best_reaction": null,
        "best_reaction_heat_no": null,
        "best_time": null,
        "best_time_heat_no": null,
        "best_max_speed": null,
        "best_max_speed_heat_no": null
      },
      "details": []
    },
    {
      "general": {
        "rider_id": 66,
        "no": 11,
        "name": "Grzegorz",
        "surname": "Walasek",
        "team_shortcut": "ZIE",
        "best_reaction": null,
        "best_reaction_heat_no": null,
        "best_time": null,
        "best_time_heat_no": null,
        "best_max_speed": null,
        "best_max_speed_heat_no": null
      },
      "details": []
    },
    {
      "general": {
        "rider_id": 147,
        "no": 12,
        "name": "Andreas",
        "surname": "Jonsson",
        "team_shortcut": "ZIE",
        "best_reaction": null,
        "best_reaction_heat_no": null,
        "best_time": null,
        "best_time_heat_no": null,
        "best_max_speed": null,
        "best_max_speed_heat_no": null
      },
      "details": []
    },
    {
      "general": {
        "rider_id": 67,
        "no": 13,
        "name": "Piotr",
        "surname": "Protasiewicz",
        "team_shortcut": "ZIE",
        "best_reaction": null,
        "best_reaction_heat_no": null,
        "best_time": null,
        "best_time_heat_no": null,
        "best_max_speed": null,
        "best_max_speed_heat_no": null
      },
      "details": []
    },
    {
      "general": {
        "rider_id": 80,
        "no": 14,
        "name": "Alex",
        "surname": "Zgardziński",
        "team_shortcut": "ZIE",
        "best_reaction": null,
        "best_reaction_heat_no": null,
        "best_time": null,
        "best_time_heat_no": null,
        "best_max_speed": null,
        "best_max_speed_heat_no": null
      },
      "details": []
    },
    {
      "general": {
        "rider_id": 70,
        "no": 15,
        "name": "Krystian",
        "surname": "Pieszczek",
        "team_shortcut": "ZIE",
        "best_reaction": null,
        "best_reaction_heat_no": null,
        "best_time": null,
        "best_time_heat_no": null,
        "best_max_speed": null,
        "best_max_speed_heat_no": null
      },
      "details": []
    }
  ],
  "attempts": {
    "regular": 6,
    "additional": 0
  }
}
